thousandeyes_sdk/administrative/__init__.py
thousandeyes_sdk/administrative/py.typed
thousandeyes_sdk/administrative/api/__init__.py
thousandeyes_sdk/administrative/api/account_groups_api.py
thousandeyes_sdk/administrative/api/permissions_api.py
thousandeyes_sdk/administrative/api/roles_api.py
thousandeyes_sdk/administrative/api/user_events_api.py
thousandeyes_sdk/administrative/api/users_api.py
thousandeyes_sdk/administrative/models/__init__.py
thousandeyes_sdk/administrative/models/account_group.py
thousandeyes_sdk/administrative/models/account_group_detail.py
thousandeyes_sdk/administrative/models/account_group_info.py
thousandeyes_sdk/administrative/models/account_group_request.py
thousandeyes_sdk/administrative/models/account_group_role.py
thousandeyes_sdk/administrative/models/account_groups.py
thousandeyes_sdk/administrative/models/agent_base.py
thousandeyes_sdk/administrative/models/agent_response.py
thousandeyes_sdk/administrative/models/audit_user_events.py
thousandeyes_sdk/administrative/models/base_role.py
thousandeyes_sdk/administrative/models/cloud_enterprise_agent_type.py
thousandeyes_sdk/administrative/models/cluster_member.py
thousandeyes_sdk/administrative/models/coordinates.py
thousandeyes_sdk/administrative/models/created_account_group.py
thousandeyes_sdk/administrative/models/created_user.py
thousandeyes_sdk/administrative/models/enterprise_agent.py
thousandeyes_sdk/administrative/models/enterprise_agent_data.py
thousandeyes_sdk/administrative/models/enterprise_agent_ipv6_policy.py
thousandeyes_sdk/administrative/models/enterprise_agent_state.py
thousandeyes_sdk/administrative/models/error.py
thousandeyes_sdk/administrative/models/error_detail.py
thousandeyes_sdk/administrative/models/error_detail_code.py
thousandeyes_sdk/administrative/models/expand_account_group_options.py
thousandeyes_sdk/administrative/models/extended_user.py
thousandeyes_sdk/administrative/models/interface_ip_mapping.py
thousandeyes_sdk/administrative/models/link.py
thousandeyes_sdk_administrative-2.23.0.dist-info/licenses/LICENSE
thousandeyes_sdk_administrative-2.23.0.dist-info/licenses/NOTICE
thousandeyes_sdk_administrative-2.23.0.dist-info/METADATA
thousandeyes_sdk_administrative-2.23.0.dist-info/WHEEL
thousandeyes_sdk_administrative-2.23.0.dist-info/top_level.txt
thousandeyes_sdk_administrative-2.23.0.dist-info/RECORD
